hermes_python-0.8.1.dist-info/RECORD
hermes_python-0.8.1.dist-info/METADATA
hermes_python-0.8.1.dist-info/top_level.txt
hermes_python-0.8.1.dist-info/WHEEL
hermes_python/__version__.py
hermes_python/__init__.py
hermes_python/hermes.py
hermes_python/api/__init__.py
hermes_python/api/ffi/tts.py
hermes_python/api/ffi/injection.py
hermes_python/api/ffi/__init__.py
hermes_python/api/ffi/dialogue.py
hermes_python/api/ffi/feedback.py
hermes_python/dylib/libhermes_mqtt_ffi.so
hermes_python/ffi/utils.py
hermes_python/ffi/wrappers.py
hermes_python/ffi/__init__.py
hermes_python/ffi/ontology/tts.py
hermes_python/ffi/ontology/injection.py
hermes_python/ffi/ontology/__init__.py
hermes_python/ffi/ontology/nlu.py
hermes_python/ffi/ontology/asr.py
hermes_python/ffi/ontology/facades.py
hermes_python/ffi/ontology/dialogue.py
hermes_python/ffi/ontology/feedback.py
hermes_python/ontology/__init__.py
hermes_python/ontology/nlu/__init__.py
hermes_python/ontology/feedback/__init__.py
hermes_python/ontology/injection/__init__.py
hermes_python/ontology/slot/__init__.py
hermes_python/ontology/dialogue/__init__.py
hermes_python/ontology/dialogue/session.py
hermes_python/ontology/dialogue/intent.py
hermes_python/ontology/asr/__init__.py
hermes_python/ontology/tts/__init__.py
