Metadata-Version: 2.1
Name: hermes-python
Version: 0.8.1
Summary: Python bindings for Snips Hermes Protocol
Home-page: UNKNOWN
Author: Anthony Reinette
Author-email: anthony.reinette@snips.ai
License: MIT
Project-URL: Documentation, https://hermespython.readthedocs.io/en/latest/
Project-URL: Tracker, https://github.com/snipsco/hermes-protocol/issues
Project-URL: Source, https://github.com/snipsco/hermes-protocol/tree/develop/platforms/hermes-python
Keywords: snips
Platform: UNKNOWN
Classifier: Programming Language :: Python :: 2
Classifier: Programming Language :: Python :: 2.7
Classifier: Programming Language :: Python :: 3.5
Provides-Extra: test
Requires-Dist: six
Requires-Dist: future
Requires-Dist: typing
Requires-Dist: enum34
Provides-Extra: test
Requires-Dist: mock; extra == 'test'
Requires-Dist: pytest; extra == 'test'
Requires-Dist: coverage; extra == 'test'
Requires-Dist: pytest-cov; extra == 'test'
